scatsutilities/__init__.py
scatsutilities/scatsutilities.py
scatsutilities-0.1.1.dist-info/LICENSE
scatsutilities-0.1.1.dist-info/WHEEL
scatsutilities-0.1.1.dist-info/METADATA
scatsutilities-0.1.1.dist-info/RECORD
